<?xml version="1.0" encoding="utf-8" ?>

<Product xmlns="http://schemas.microsoft.com/developer/2004/01/bootstrapper" 
         ProductCode="EULA.Bootstrap.Component" >
  <!-- Defines list of files to be copied on build -->
  <PackageFiles>
    <PackageFile Name="en/eula.txt"/>
  </PackageFiles>

  <Commands>
    <Command PackageFile="en/eula.txt" Arguments='' >
      <ExitCodes>
        <DefaultExitCode Result="Fail" FormatMessageFromSystem="true" String="GeneralFailure" />
      </ExitCodes>
    </Command>
  </Commands>
</Product>